call_openai_gpt.py
call_openai_gpt-1.0.0.dist-info/METADATA
call_openai_gpt-1.0.0.dist-info/WHEEL
call_openai_gpt-1.0.0.dist-info/entry_points.txt
call_openai_gpt-1.0.0.dist-info/top_level.txt
call_openai_gpt-1.0.0.dist-info/RECORD
