Metadata-Version: 2.1
Name: call-openai-gpt
Version: 1.0.0
Requires-Dist: requests
Requires-Dist: python-dotenv
